{
  "parent": "minecraft:recipes/root",
  "criteria": {
    "has_the_recipe": {
      "conditions": {
        "recipe": "bensaddons:yellow_celosia_cut"
      },
      "trigger": "minecraft:recipe_unlocked"
    },
    "has_yellow_celosia": {
      "conditions": {
        "items": [
          {
            "items": [
              "bensaddons:yellow_celosia_bush_top"
            ]
          }
        ]
      },
      "trigger": "minecraft:inventory_changed"
    }
  },
  "requirements": [
    [
      "has_the_recipe",
      "has_yellow_celosia"
    ]
  ],
  "rewards": {
    "recipes": [
      "bensaddons:yellow_celosia_cut"
    ]
  },
  "sends_telemetry_event": false
}